mcp/file/v1/file_pb2.py
mcp/operand/v1/operand_pb2.py
mcp/tenant/v1/tenant_pb2.py
operand/client.py
operand-0.2.9.dist-info/LICENSE
operand-0.2.9.dist-info/METADATA
operand-0.2.9.dist-info/WHEEL
operand-0.2.9.dist-info/top_level.txt
operand-0.2.9.dist-info/RECORD
